kjpy/__init__.py
kjpy/class_helpers/serializable_csv.py
kjpy/collections/mapping_class.py
kjpy/collections/sequence_class.py
kjpy/collections/serializable_bson_class.py
kjpy/collections/serializable_class.py
kjpy/concurrent/concurrent_manager.py
kjpy/concurrent/workers.py
kjpy/concurrent/listeners/db_listener.py
kjpy/concurrent/listeners/listener.py
kjpy/concurrent/listeners/listener_message_hub.py
kjpy/concurrent/worker_messages/mongo_message_abstract.py
kjpy/concurrent/worker_messages/mongo_query.py
kjpy/concurrent/worker_messages/mongo_update.py
kjpy/concurrent/worker_messages/worker_stats.py
kjpy/concurrent/worker_messages/worker_metadata_store/worker_metadata.py
kjpy/concurrent/worker_messages/worker_metadata_store/worker_metadata_manager.py
kjpy/data/data_handler.py
kjpy/data/data_io_handler.py
kjpy/data/misc.py
kjpy/data/unit_test_handler.py
kjpy/decorators/beautiful_soup_decorators.py
kjpy/decorators/log_time.py
kjpy/format/format_time.py
kjpy/transforms/json_object_mapper.py
kjpy/transforms/transform_deep_object.py
kjpy/transforms/transform_field_helpers.py
kjpy-0.0.7.dist-info/LICENSE
kjpy-0.0.7.dist-info/METADATA
kjpy-0.0.7.dist-info/WHEEL
kjpy-0.0.7.dist-info/top_level.txt
kjpy-0.0.7.dist-info/RECORD
