Metadata-Version: 2.1
Name: kjpy
Version: 0.0.7
Summary: A library to make python easier
Author-email: KJ Price <kjprice12@gmail.com>
Project-URL: Homepage, https://github.com/kjprice/kjpy
Project-URL: Bug Tracker, https://github.com/kjprice/kjpy/issues
Classifier: Programming Language :: Python :: 3
Classifier: License :: OSI Approved :: MIT License
Classifier: Operating System :: OS Independent
Requires-Python: >=3.7
License-File: LICENSE
